README.rst
setup.py
src/verschemes/__init__.py
src/verschemes/_types.py
src/verschemes/_version.py
src/verschemes/pep440.py
src/verschemes/postgresql.py
src/verschemes/python.py
src/verschemes/xorg.py
src/verschemes.egg-info/PKG-INFO
src/verschemes.egg-info/SOURCES.txt
src/verschemes.egg-info/dependency_links.txt
src/verschemes.egg-info/requires.txt
src/verschemes.egg-info/top_level.txt
src/verschemes/future/__init__.py
src/verschemes/future/newstr.py
src/verschemes/future/newsuper.py
src/verschemes/future/newtype.py