Metadata-Version: 1.1
Name: verschemes
Version: 1.1.0
Summary: Version identifier management
Home-page: https://github.com/gnuworldman/verschemes
Author: Craig Hurd-Rindy
Author-email: gnuworldman@gmail.com
License: UNKNOWN
Platform: UNKNOWN
Classifier: Development Status :: 5 - Production/Stable
Classifier: Intended Audience :: Developers
Classifier: License :: OSI Approved :: GNU General Public License v3 (GPLv3)
Classifier: Programming Language :: Python :: 2.7
Classifier: Programming Language :: Python :: 3.3
Classifier: Programming Language :: Python :: 3.4
Classifier: Topic :: Utilities
